jsoncodable/__init__.py
jsoncodable/_compressor.py
jsoncodable/jsoncodable.py
jsoncodable/enums/__init__.py
jsoncodable/enums/compression_algorithm.py
jsoncodable-0.1.7.dist-info/LICENSE
jsoncodable-0.1.7.dist-info/METADATA
jsoncodable-0.1.7.dist-info/WHEEL
jsoncodable-0.1.7.dist-info/top_level.txt
jsoncodable-0.1.7.dist-info/RECORD
