Metadata-Version: 2.1
Name: jsoncodable
Version: 0.1.7
Summary: to_dict
Home-page: https://github.com/kkristof200/py_jsoncodable
Author: Kristof
License: UNKNOWN
Platform: UNKNOWN
Classifier: Programming Language :: Python :: 3
Classifier: License :: OSI Approved :: MIT License
Classifier: Operating System :: OS Independent
Requires-Python: >=3.5
